<annotation>
  <folder>images</folder>
  <filename>frame375.jpg</filename>
  <segmented>0</segmented>
  <size>
    <width>1920</width>
    <height>1080</height>
    <depth>3</depth>
  </size>
  <object>
    <name>motorbike</name>
    <pose>Unspecified</pose>
    <truncated>0</truncated>
    <difficult>0</difficult>
    <bndbox>
      <xmin>626</xmin>
      <ymin>11</ymin>
      <xmax>727</xmax>
      <ymax>150</ymax>
    </bndbox>
  </object>
  <object>
    <name>motorbike</name>
    <pose>Unspecified</pose>
    <truncated>0</truncated>
    <difficult>0</difficult>
    <bndbox>
      <xmin>591</xmin>
      <ymin>239</ymin>
      <xmax>700</xmax>
      <ymax>456</ymax>
    </bndbox>
  </object>
  <object>
    <name>motorbike</name>
    <pose>Unspecified</pose>
    <truncated>0</truncated>
    <difficult>0</difficult>
    <bndbox>
      <xmin>560</xmin>
      <ymin>545</ymin>
      <xmax>734</xmax>
      <ymax>866</ymax>
    </bndbox>
  </object>
  <object>
    <name>motorbike</name>
    <pose>Unspecified</pose>
    <truncated>0</truncated>
    <difficult>0</difficult>
    <bndbox>
      <xmin>425</xmin>
      <ymin>247</ymin>
      <xmax>545</xmax>
      <ymax>479</ymax>
    </bndbox>
  </object>
  <object>
    <name>motorbike</name>
    <pose>Unspecified</pose>
    <truncated>0</truncated>
    <difficult>0</difficult>
    <bndbox>
      <xmin>212</xmin>
      <ymin>352</ymin>
      <xmax>355</xmax>
      <ymax>592</ymax>
    </bndbox>
  </object>
  <object>
    <name>motorbike</name>
    <pose>Unspecified</pose>
    <truncated>0</truncated>
    <difficult>0</difficult>
    <bndbox>
      <xmin>293</xmin>
      <ymin>588</ymin>
      <xmax>483</xmax>
      <ymax>870</ymax>
    </bndbox>
  </object>
</annotation>
