<annotation>
  <folder>images</folder>
  <filename>frame21.jpg</filename>
  <segmented>0</segmented>
  <size>
    <width>1920</width>
    <height>1080</height>
    <depth>3</depth>
  </size>
  <object>
    <name>motorbike</name>
    <pose>Unspecified</pose>
    <truncated>0</truncated>
    <difficult>0</difficult>
    <bndbox>
      <xmin>1234</xmin>
      <ymin>263</ymin>
      <xmax>1338</xmax>
      <ymax>495</ymax>
    </bndbox>
  </object>
  <object>
    <name>motorbike</name>
    <pose>Unspecified</pose>
    <truncated>0</truncated>
    <difficult>0</difficult>
    <bndbox>
      <xmin>1443</xmin>
      <ymin>731</ymin>
      <xmax>1648</xmax>
      <ymax>1060</ymax>
    </bndbox>
  </object>
  <object>
    <name>motorbike</name>
    <pose>Unspecified</pose>
    <truncated>0</truncated>
    <difficult>0</difficult>
    <bndbox>
      <xmin>560</xmin>
      <ymin>112</ymin>
      <xmax>661</xmax>
      <ymax>305</ymax>
    </bndbox>
  </object>
  <object>
    <name>motorbike</name>
    <pose>Unspecified</pose>
    <truncated>0</truncated>
    <difficult>0</difficult>
    <bndbox>
      <xmin>479</xmin>
      <ymin>61</ymin>
      <xmax>556</xmax>
      <ymax>228</ymax>
    </bndbox>
  </object>
  <object>
    <name>motorbike</name>
    <pose>Unspecified</pose>
    <truncated>0</truncated>
    <difficult>0</difficult>
    <bndbox>
      <xmin>274</xmin>
      <ymin>263</ymin>
      <xmax>444</xmax>
      <ymax>503</ymax>
    </bndbox>
  </object>
</annotation>
